easyvanity/__init__.py
easyvanity/client.py
easyvanity/lib/__init__.py
easyvanity/lib/util/__init__.py
easyvanity/lib/util/exceptions.py
easyvanity/lib/util/objects.py
easyvanity.py-0.1.4.dist-info/LICENSE
easyvanity.py-0.1.4.dist-info/METADATA
easyvanity.py-0.1.4.dist-info/WHEEL
easyvanity.py-0.1.4.dist-info/top_level.txt
easyvanity.py-0.1.4.dist-info/RECORD
