Metadata-Version: 2.1
Name: easyvanity.py
Version: 0.1.4
Summary: Easily create a vanity structure!
Home-page: UNKNOWN
Author: Team Wezacon
Author-email: wezacon.com@gmail.com
License: AGPL
Keywords: vanity,bots-py,wezacon
Platform: UNKNOWN
Requires-Dist: setuptools
Requires-Dist: requests
Requires-Dist: six
Requires-Dist: ujson
Requires-Dist: pymongo
Requires-Dist: dnspython
